{
  "$schema": "https://vega.github.io/schema/vega/v5.json",
  "title": "Greenhouse Gas Emissions by Sector",
  "width": 1000,
  "height": 300,
  "signals": [
    {"name": "PI", "value": 3.141592653589793},
    {"name": "fontFactor", "value": 0.5},
    {"name": "unit", "value": " MtCO2e"}
  ],
  "data": [
    {
      "name": "ticks",
      "values": [0, 100000, 200000, 330358.21]
    }
  ],
  "marks": [
    {
      "type": "group",
      "title": "Energy Emission",
      "encode": {
        "enter": {
          "x": {"value": 50},
          "y": {"value": 50},
          "width": {"value": 150},
          "height": {"value": 250}
        }
      },
      "signals": [
        {"name": "mainValueEnergy", "value": 259326.11},
        {"name": "centerX", "value": 75},
        {"name": "centerY", "value": 125},
        {"name": "outerRadius", "value": 100},
        {"name": "innerRadius", "value": 80},
        {"name": "fillColor", "value": "#ff0000"},
        {"name": "backgroundColor", "value": "#ddd"},
        {"name": "ticksColor", "value": "#000"},
        {"name": "needleColor", "value": "#000"},
        {"name": "needleSize", "value": 100}
      ],
      "scales": [
        {
          "name": "gaugeScaleEnergy",
          "type": "linear",
          "domain": [0, 330358.21],
          "range": [-1.5708, 1.5708]
        }
      ],
      "marks": [
        {
          "type": "arc",
          "encode": {
            "enter": {
              "x": {"signal": "centerX"},
              "y": {"signal": "centerY"},
              "startAngle": {"value": -1.5708},
              "endAngle": {"value": 1.5708},
              "outerRadius": {"signal": "outerRadius"},
              "innerRadius": {"signal": "innerRadius"},
              "fill": {"signal": "backgroundColor"}
            }
          }
        },
        {
          "type": "arc",
          "encode": {
            "enter": {"startAngle": {"value": -1.5708}},
            "update": {
              "x": {"signal": "centerX"},
              "y": {"signal": "centerY"},
              "innerRadius": {"signal": "innerRadius"},
              "outerRadius": {"signal": "outerRadius"},
              "endAngle": {"scale": "gaugeScaleEnergy", "signal": "mainValueEnergy"},
              "fill": {"signal": "fillColor"}
            }
          }
        },
        {
          "type": "arc",
          "description": "ticks on the arc",
          "from": {"data": "ticks"},
          "encode": {
            "enter": {
              "x": {"signal": "centerX"},
              "y": {"signal": "centerY"},
              "outerRadius": {"signal": "outerRadius"},
              "innerRadius": {"signal": "outerRadius -20"},
              "startAngle": {"scale": "gaugeScaleEnergy", "field": "data"},
              "endAngle": {"scale": "gaugeScaleEnergy", "field": "data"},
              "stroke": {"signal": "ticksColor"},
              "strokeWidth": {"value": 1}
            }
          }
        },
        {
          "type": "text",
          "encode": {
            "enter": {
              "x": {"signal": "centerX"},
              "y": {"signal": "centerY + 50"}, 
              "text": {"signal": "format(mainValueEnergy, '.2f') + unit"},
              "align": {"value": "center"},
              "baseline": {"value": "top"},
              "fontSize": {"signal": "fontFactor * 30"} 
            }
          }
        },
        {
          "type": "symbol",
          "name": "needle",
          "encode": {
            "enter": {
              "x": {"signal": "centerX"},
              "y": {"signal": "centerY"},
              "angle": {"scale": "gaugeScaleEnergy", "signal": "mainValueEnergy"},
              "stroke": {"signal": "needleColor"},
              "fill": {"signal": "needleColor"}
            }
          }
        }
      ]
    },
    {
      "type": "group",
      "title": "Industrial Emission",
      "encode": {
        "enter": {
          "x": {"value": 288},
          "y": {"value": 50},
          "width": {"value": 150},
          "height": {"value": 250}
        }
      },
      "signals": [
        {"name": "mainValueIndustrial", "value": 32853.8},
        {"name": "centerX", "value": 75},
        {"name": "centerY", "value": 125},
        {"name": "outerRadius", "value": 100},
        {"name": "innerRadius", "value": 80},
        {"name": "fillColor", "value": "#ff8000"},
        {"name": "backgroundColor", "value": "#ddd"},
        {"name": "ticksColor", "value": "#000"},
        {"name": "needleColor", "value": "#000"},
        {"name": "needleSize", "value": 100}
      ],
      "scales": [
        {
          "name": "gaugeScaleIndustrial",
          "type": "linear",
          "domain": [0, 330358.21],
          "range": [-1.5708, 1.5708]
        }
      ],
      "marks": [
        {
          "type": "arc",
          "encode": {
            "enter": {
              "x": {"signal": "centerX"},
              "y": {"signal": "centerY"},
              "startAngle": {"value": -1.5708},
              "endAngle": {"value": 1.5708},
              "outerRadius": {"signal": "outerRadius"},
              "innerRadius": {"signal": "innerRadius"},
              "fill": {"signal": "backgroundColor"}
            }
          }
        },
        {
          "type": "arc",
          "encode": {
            "enter": {"startAngle": {"value": -1.5708}},
            "update": {
              "x": {"signal": "centerX"},
              "y": {"signal": "centerY"},
              "innerRadius": {"signal": "innerRadius"},
              "outerRadius": {"signal": "outerRadius"},
              "endAngle": {"scale": "gaugeScaleIndustrial", "signal": "mainValueIndustrial"},
              "fill": {"signal": "fillColor"}
            }
          }
        },
        {
          "type": "arc",
          "description": "ticks on the arc",
          "from": {"data": "ticks"},
          "encode": {
            "enter": {
              "x": {"signal": "centerX"},
              "y": {"signal": "centerY"},
              "outerRadius": {"signal": "outerRadius"},
              "innerRadius": {"signal": "outerRadius -20"},
              "startAngle": {"scale": "gaugeScaleIndustrial", "field": "data"},
              "endAngle": {"scale": "gaugeScaleIndustrial", "field": "data"},
              "stroke": {"signal": "ticksColor"},
              "strokeWidth": {"value": 1}
            }
          }
        },
        {
          "type": "text",
          "encode": {
            "enter": {
              "x": {"signal": "centerX"},
              "y": {"signal": "centerY + 50"},
              "text": {"signal": "format(mainValueIndustrial, '.2f') + unit"},
              "align": {"value": "center"},
              "baseline": {"value": "top"},
              "fontSize": {"signal": "fontFactor * 30"}
            }
          }
        },
        {
          "type": "symbol",
          "name": "needle",
          "encode": {
            "enter": {
              "x": {"signal": "centerX"},
              "y": {"signal": "centerY"},
              "angle": {"scale": "gaugeScaleIndustrial", "signal": "mainValueIndustrial"},
              "stroke": {"signal": "needleColor"},
              "fill": {"signal": "needleColor"}
            }
          }
        }
      ]
    },
    {
      "type": "group",
      "title": "Agriculture Emission",
      "encode": {
        "enter": {
          "x": {"value": 526},
          "y": {"value": 50},
          "width": {"value": 150},
          "height": {"value": 250}
        }
      },
      "signals": [
        {"name": "mainValueAgriculture", "value": 9921.71},
        {"name": "centerX", "value": 75},
        {"name": "centerY", "value": 125},
        {"name": "outerRadius", "value": 100},
        {"name": "innerRadius", "value": 80},
        {"name": "fillColor", "value": "#00ff00"},
        {"name": "backgroundColor", "value": "#ddd"},
        {"name": "ticksColor", "value": "#000"},
        {"name": "needleColor", "value": "#000"},
        {"name": "needleSize", "value": 100}
      ],
      "scales": [
        {
          "name": "gaugeScaleAgriculture",
          "type": "linear",
          "domain": [0, 330358.21],
          "range": [-1.5708, 1.5708]
        }
      ],
      "marks": [
        {
          "type": "arc",
          "encode": {
            "enter": {
              "x": {"signal": "centerX"},
              "y": {"signal": "centerY"},
              "startAngle": {"value": -1.5708},
              "endAngle": {"value": 1.5708},
              "outerRadius": {"signal": "outerRadius"},
              "innerRadius": {"signal": "innerRadius"},
              "fill": {"signal": "backgroundColor"}
            }
          }
        },
        {
          "type": "arc",
          "encode": {
            "enter": {"startAngle": {"value": -1.5708}},
            "update": {
              "x": {"signal": "centerX"},
              "y": {"signal": "centerY"},
              "innerRadius": {"signal": "innerRadius"},
              "outerRadius": {"signal": "outerRadius"},
              "endAngle": {"scale": "gaugeScaleAgriculture", "signal": "mainValueAgriculture"},
              "fill": {"signal": "fillColor"}
            }
          }
        },
        {
          "type": "arc",
          "description": "ticks on the arc",
          "from": {"data": "ticks"},
          "encode": {
            "enter": {
              "x": {"signal": "centerX"},
              "y": {"signal": "centerY"},
              "outerRadius": {"signal": "outerRadius"},
              "innerRadius": {"signal": "outerRadius - 20"},
              "startAngle": {"scale": "gaugeScaleAgriculture", "field": "data"},
              "endAngle": {"scale": "gaugeScaleAgriculture", "field": "data"},
              "stroke": {"signal": "ticksColor"},
              "strokeWidth": {"value": 1}
            }
          }
        },
        {
          "type": "text",
          "encode": {
            "enter": {
              "x": {"signal": "centerX"},
              "y": {"signal": "centerY + 50"},
              "text": {"signal": "format(mainValueAgriculture, '.2f') + unit"},
              "align": {"value": "center"},
              "baseline": {"value": "top"},
              "fontSize": {"signal": "fontFactor * 30"}
            }
          }
        },
        {
          "type": "symbol",
          "name": "needle",
          "encode": {
            "enter": {
              "x": {"signal": "centerX"},
              "y": {"signal": "centerY"},
              "angle": {"scale": "gaugeScaleAgriculture", "signal": "mainValueAgriculture"},
              "stroke": {"signal": "needleColor"},
              "fill": {"signal": "needleColor"}
            }
          }
        }
      ]
    },
    {
      "type": "group",
      "title": "Waste Emission",
      "encode": {
        "enter": {
          "x": {"value": 764},
          "y": {"value": 50},
          "width": {"value": 150},
          "height": {"value": 250}
        }
      },
      "signals": [
        {"name": "mainValueWaste", "value": 28256.59},
        {"name": "centerX", "value": 75},
        {"name": "centerY", "value": 125},
        {"name": "outerRadius", "value": 100},
        {"name": "innerRadius", "value": 80},
        {"name": "fillColor", "value": "#0000ff"},
        {"name": "backgroundColor", "value": "#ddd"},
        {"name": "ticksColor", "value": "#000"},
        {"name": "needleColor", "value": "#000"},
        {"name": "needleSize", "value": 100}
      ],
      "scales": [
        {
          "name": "gaugeScaleWaste",
          "type": "linear",
          "domain": [0, 330358.21],
          "range": [-1.5708, 1.5708]
        }
      ],
      "marks": [
        {
          "type": "arc",
          "encode": {
            "enter": {
              "x": {"signal": "centerX"},
              "y": {"signal": "centerY"},
              "startAngle": {"value": -1.5708},
              "endAngle": {"value": 1.5708},
              "outerRadius": {"signal": "outerRadius"},
              "innerRadius": {"signal": "innerRadius"},
              "fill": {"signal": "backgroundColor"}
            }
          }
        },
        {
          "type": "arc",
          "encode": {
            "enter": {"startAngle": {"value": -1.5708}},
            "update": {
              "x": {"signal": "centerX"},
              "y": {"signal": "centerY"},
              "innerRadius": {"signal": "innerRadius"},
              "outerRadius": {"signal": "outerRadius"},
              "endAngle": {"scale": "gaugeScaleWaste", "signal": "mainValueWaste"},
              "fill": {"signal": "fillColor"}
            }
          }
        },
        {
          "type": "arc",
          "description": "ticks on the arc",
          "from": {"data": "ticks"},
          "encode": {
            "enter": {
              "x": {"signal": "centerX"},
              "y": {"signal": "centerY"},
              "outerRadius": {"signal": "outerRadius"},
              "innerRadius": {"signal": "outerRadius - 20"},
              "startAngle": {"scale": "gaugeScaleWaste", "field": "data"},
              "endAngle": {"scale": "gaugeScaleWaste", "field": "data"},
              "stroke": {"signal": "ticksColor"},
              "strokeWidth": {"value": 1}
            }
          }
        },
        {
          "type": "text",
          "encode": {
            "enter": {
              "x": {"signal": "centerX"},
              "y": {"signal": "centerY + 50"},
              "text": {"signal": "format(mainValueWaste, '.2f') + unit"},
              "align": {"value": "center"},
              "baseline": {"value": "top"},
              "fontSize": {"signal": "fontFactor * 30"}
            }
          }
        },
        {
          "type": "symbol",
          "name": "needle",
          "encode": {
            "enter": {
              "x": {"signal": "centerX"},
              "y": {"signal": "centerY"},
              "angle": {"scale": "gaugeScaleWaste", "signal": "mainValueWaste"},
              "stroke": {"signal": "needleColor"},
              "fill": {"signal": "needleColor"}
            }
          }
        }
      ]
    }
  ]
}
